{"1348684713813180416": {"username": "kerrywashington", "bio": "#LittleFiresEverywhere on @Hulu \ud83d\udd25\ud83d\udd25\ud83d\udd25\ud83d\udd25 For new projects follow @simpsonstreet 718-400-7118", "cluster": null}, "1348684929668968449": {"username": "MsOCHubbard", "bio": "", "cluster": -1}, "1348684953874288641": {"username": "Hollandorange1", "bio": "", "cluster": -1}, "1348684965895135232": {"username": "ReanSelpink", "bio": "I'm so RARE 23. Men, Student & SELENATOR and SWIFTIE", "cluster": -1}, "1348684988632412164": {"username": "Bjulias422", "bio": "\u25aa\ufe0eProj Co/Louis Berger \u25aaExec/GW\n\u25aa\ufe0eFed Gov Career/US Congress Legis Staff\u25aa\ufe0eCofounder/1st elected \u2640 Pres CLSA\u25aaFounder/JSB Nonprofit 4 Eldercare 16yrs\n#MARYGIRLS\ud83c\udf0e", "cluster": 84}, "1348684997557948419": {"username": "slimpickens2916", "bio": "College educated with graduate degrees. Professor, retired; Florida State University alumni. Staunch Democrat, Resister Sussexes supporter. Equality for all.", "cluster": -1}, "1348685083264348168": {"username": "dupri13_leo", "bio": "", "cluster": 48}, "1348685157616685056": {"username": "MsMicaLuv", "bio": "What is Love without a mission? #LoverofMusic #Raidernation #As #Celtics #Sharks My tweets has no reflection on my employer", "cluster": -1}, "1348685367201951744": {"username": "ComposedClaytor", "bio": "{He/Him} Now: @VotingIsLocal OH Campaign Manager Alum:@OhioForWarren,@Donnelly4Ohio,@MiamiUniversity& @ShakerSchools #RTs\u2260Endorsements Opinions=MyOwn \u039a\u0391\u03a8~\u03a6\u03bd\u03a0", "cluster": -1}, "1348685728990064644": {"username": "ReedTamala", "bio": "To Be Young Gifted and black #top20  NBA bound", "cluster": -1}, "1348685774607306753": {"username": "allmyloveDre", "bio": "~Perfectly Imperfect \ud83d\udc95\ud83d\udc9e~Living My Best Life\ud83c\udfb6         ~Biden/Harris2020\ud83c\uddfa\ud83c\uddf8", "cluster": -1}, "1348685820971069443": {"username": "Ares5280", "bio": "Just a cat doing cat stuff", "cluster": -1}, "1348686205714640896": {"username": "coolsamd", "bio": "", "cluster": 59}, "1348686667641548800": {"username": "FilmTVDiversity", "bio": "Dedicated to Activism, the Support, Promotion and Celebration of Diversity and Inclusion in the Arts while covering and offering Industry news & resources", "cluster": -1}, "1348686689099776000": {"username": "DopModi", "bio": "", "cluster": 84}, "1348687033019994112": {"username": "peterson_mona", "bio": "", "cluster": 84}, "1348687109192822784": {"username": "KDL0888", "bio": "Kim. lesbian. sister. veteran. human. mother. \n#Shaw -Oh, There was plenty of sucking! \ud83d\ude0d\n#Root -I've Got Her Harry! \ud83d\ude0d\n#POI #Shoot #WynonnaEarp #Avalance", "cluster": -1}, "1348688527165419525": {"username": "Imiguel78", "bio": "Runner/Selfmade/ activista incansable/ fan a todos los deportes, so\u00f1ador /Freethinker\nMiguel \u00c1ngel Calder\u00f3n Fern\u00e1ndez +1524774169180", "cluster": -1}, "1348689370598039558": {"username": "JoanGrady5", "bio": "Funny", "cluster": 84}, "1348689407587590155": {"username": "ChristineVSmith", "bio": "", "cluster": -1}, "1348689594246684675": {"username": "JemilaEA", "bio": "Loyal  |  Brave |  True |  Devotion to Family\n                     Daughter of Halima, MA Econ | Subscribe to my #YouTube. link below...\n\n@KitchenClatters #MUFC", "cluster": 15}, "1348690023168831493": {"username": "brandonmscales", "bio": "", "cluster": 46}, "1348690108065718279": {"username": "Yizzzz2", "bio": "", "cluster": -1}, "1348692701886238723": {"username": "CommonSense2d", "bio": "Help for the 70,000,000+ lost souls who voted for #RepubliKKKansKillUS. \nAgainst racism, sexism, #GOPTraitors, #PutinsGQP.\nElections matter. #BLM", "cluster": 84}, "1348694061373386756": {"username": "QueensOfWarrior", "bio": "We Are Who We Choose To Be & Arrive Where We're Meant To. So Love Life, Love Yourself & Truly Live The Life You Want, But Always Stay True To Who You Are.", "cluster": -1}, "1348694429373263881": {"username": "mvmblackdogs_g", "bio": "Dog rescuer. Traveler. Adventurer. Thinker. Crime Victim Advocate. Restorative Justice Practitioner. Colorado native.", "cluster": 84}, "1348694778020573185": {"username": "sugabrown2020", "bio": "", "cluster": -1}, "1348695055645569024": {"username": "em_jaykay_em", "bio": "\u00af\\_(\u30c4)_/\u00af\n\n(she/her)", "cluster": 44}, "1348698723853938688": {"username": "martins4xf", "bio": "", "cluster": -1}, "1348699701000990721": {"username": "VonnieLowery", "bio": "Big Kid , Lover of Family, Most of all I love TV!! I am all these things and much more!!", "cluster": -1}, "1348700295535222787": {"username": "RianFike", "bio": "Art Teacher. Writer. Chaos Magician.", "cluster": -1}, "1348707324127567874": {"username": "ZintelM", "bio": "Not a man. Not a chief. Not a guy. Not a nigga. Not a bra", "cluster": 90}, "1348722607718342656": {"username": "sframtdr", "bio": "#NoUnityWithoutJustice WeRNotDone #EndWhiteSupremacy #BLM #SaveThePlanet END Exploitation of MarginalizedPeople around the \ud83c\udf0e \u2764 Retweets Replies\u2260 Endorsements", "cluster": 84}, "1348722868234956802": {"username": "ktjazz14", "bio": "", "cluster": -1}, "1348723091690708994": {"username": "Maria_Emmm", "bio": "Views are my own. Yes, even the retweets. \ud83d\ude09", "cluster": 84}, "1348723405256851457": {"username": "cuddilopes", "bio": "Sky Daddy | Rolling stone | Writer | Man with the tilted halo | #AlaskaGrown IG: cuddilopes \ud83d\udce7: wdloper22@gmail.com", "cluster": 90}, "1348723439830503424": {"username": "DE92633354", "bio": "All things politics and me Followed by @glennkirschner2 @shomaristone #TeamJustice #BidenHarris #LGBTQ ally Blessed/Wear a mask debutant", "cluster": -1}, "1348723540523159559": {"username": "AndersonMona", "bio": "", "cluster": 84}, "1348724117839736832": {"username": "SoCaltoDMV", "bio": "Organize...Protest.... VOTE to make changes....\ud83c\uddea\ud83c\uddf7\ud83c\uddfa\ud83c\uddf8\ud83d\udc95", "cluster": 84}, "1348724200928894982": {"username": "MagalieAlexis1", "bio": "Visionary  leader. Educator of theYear.Advocate4children.TransformativeChangeAgent.TC@Columbia University Cahn Fellow. Future Superintendent Academy Fellow.", "cluster": -1}, "1348725974146363392": {"username": "DeniseParringt4", "bio": "", "cluster": 84}, "1348729300476981257": {"username": "raffman64_john", "bio": "", "cluster": -1}, "1348732789567467523": {"username": "Official_JesseT", "bio": "", "cluster": -1}, "1348744586722594816": {"username": "SerenaC123", "bio": "", "cluster": -1}, "1348746130318876673": {"username": "MLecler19817979", "bio": "Voting Rights Act of 1965 gave the federal government the authority to take over voter registration in counties with a pattern of persistent discrimination.\u00a0", "cluster": 84}, "1348747227339124736": {"username": "FirmeJoe", "bio": "", "cluster": -1}, "1348748435520892930": {"username": "rolandsmartin", "bio": "host, #RolandMartinUnfiltered daily digital show; senior analyst, @tjmshow; author; international speaker; CEO, Nu Vision Media", "cluster": -1}, "1348748759853891585": {"username": "rjcaliente", "bio": "Attorney, Arbitrator, Mediator - Legal Solutions and Dispute Resolution", "cluster": -1}, "1348748999323496450": {"username": "hortensiaframos", "bio": "Retired assignment editor at WIPR Channel 6 PBS Station . Love family, friends and country .", "cluster": 84}, "1348749037768384513": {"username": "avoidchaos", "bio": "Boss bitch. Black women are usually right but sometimes we f*ck up and hug convicted murderers.\ud83e\udd37\ud83c\udffd\u200d\u2640\ufe0f Free your mind, your behind shall follow.", "cluster": -1}, "1348749120631091200": {"username": "4RealForeal", "bio": "\ud83d\ude0e", "cluster": -1}, "1348749947483525122": {"username": "Bourgeau", "bio": "", "cluster": -1}, "1348751063441051648": {"username": "champa10", "bio": "Sr. Manager in the Affordable Housing/Tax Credit industry. \nPolitical junky/DEMOCRAT.  My thoughts are owned by me, and I have no patience for idiots. #Resister", "cluster": 84}, "1348753127760080899": {"username": "karlawaggener", "bio": "", "cluster": 84}, "1348753308735983616": {"username": "lynn4257", "bio": "#YR #Days #GH #BoldandBeautiful Love all soaps! \u2764\ufe0f\u2764\ufe0f \u201cIf you surrendered to the air, you could ride it.\u201d -Toni Morrison #TeamDevon #TeamAmanda", "cluster": -1}, "1348755139914592258": {"username": "_EllE_2125", "bio": "", "cluster": -1}, "1348756808387715081": {"username": "HeiressMommy", "bio": "Wife\u2665\ufe0fMama \u265b FEMINIST\ud83e\uddd8\u200d\u2640\ufe0fYoga, BookMusicArt\ud83d\udcdaEconomist/Law, Writer+CoCEO ES Co\ud83c\udf0eLegacyBuilder #LGBTQAlly, #StopAntiSemitism #StopAsianHate #BLACKLIVESMATTER", "cluster": -1}, "1348757648271843329": {"username": "Moneymac101", "bio": "Someone who loves music, life, family and everything else.", "cluster": 45}, "1348758403670306820": {"username": "Shawna_Janell", "bio": "Mother, wife, artist,-ALL black ALL day-,  DST, criminal justice reform, somewhat of a political junkie, holistic enthusiast\n\u270c\ud83c\udffe\u2764\ud83e\uddd8\ud83c\udffe\u200d\u2640\ufe0f", "cluster": 84}, "1348760610293616650": {"username": "soamazing61", "bio": "", "cluster": -1}, "1348761563239366661": {"username": "Nesha2795", "bio": "\u201cStop pretending that I have it all together, & if I\u2019m scared, be scared. Allow it. Release it. Move on.\u201d-Beyonc\u00e9", "cluster": -1}, "1348771845986779137": {"username": "gimli0413", "bio": "Black Woman, Democrat, Ohioan. Focus: gerrymandering, racial injustice, gun control, healthcare. I curse. A lot. #JoyfulWarrior #BidenHarrisWon", "cluster": 84}, "1348772456878792704": {"username": "MinisterX2", "bio": "I say what I mean, I mean what I say! You don\u2019t like it, block me, I\u2019m not here to make you feel comfortable!", "cluster": -1}, "1348778940639436800": {"username": "poppabugg", "bio": "Social Media Oversharer. Colored People Curator. Idea Nurturer. Kid Motivator. Brooklyn Community Enthusiast. Cappuccino Craver. Mixed Music Shuffler. TV Guy.", "cluster": -1}, "1348779341149319168": {"username": "RiveraJeanne", "bio": "", "cluster": 84}, "1348782918093705216": {"username": "Newhouse_Young", "bio": "\u00d7Educator + Reader/Writer + Lyrical/Loud.          \n        \u00d7Progressive + Opportunity of Color + Voice \n          \u00d7Recognition of Blackness + Justice/Equity", "cluster": -1}, "1348785253742071809": {"username": "blmmammo", "bio": "BLM VP Kamala Harris is my spirit warrior,  President Biden is my solace.", "cluster": 84}, "1348810187965128704": {"username": "simonesydnor1", "bio": "I am a retired Physical and Health Educator, very much into issues affecting Social Justice and Women's Rights.", "cluster": 84}, "1348812055583797250": {"username": "SmartOn80149888", "bio": "Making a difference", "cluster": 84}, "1348812503086727175": {"username": "redpete704", "bio": "", "cluster": -1}, "1348818548827820033": {"username": "khlumsyy_t", "bio": "Our humanity is not negotiable #oromoprotests", "cluster": 61}, "1348819843609481226": {"username": "dlu2hnbh", "bio": "", "cluster": -1}, "1348826973657821184": {"username": "iamsportscourts", "bio": "", "cluster": 59}, "1348828232573976576": {"username": "misskesha2412", "bio": "", "cluster": 53}, "1348830492439801861": {"username": "Tania29960888", "bio": "", "cluster": -1}, "1348836835292807168": {"username": "Thayes62766", "bio": "", "cluster": -1}, "1348847014159769601": {"username": "80rockstar", "bio": "Loving life~my family", "cluster": -1}, "1348849200142950402": {"username": "Patterson412", "bio": "Retired Special Education Teacher", "cluster": 84}, "1348854256938471424": {"username": "violetesq", "bio": "Attorney/Law Professor/Musician \ud83c\udf38Passionate. Purple. Positivity\ud83d\udc9cVioletB\ud83c\udf38InterACTive dcbt\ud83d\udc9cdedication\u2022courage\u2022beauty\u2022truth\ud83d\udc9c #prince4ever #PRINCEspiration", "cluster": 84}, "1348860027273097216": {"username": "Celebratelife77", "bio": "Travel consultant looking to travel the world and help others do the same.", "cluster": -1}, "1348900674034163713": {"username": "rainwatertones", "bio": "Living In Love that is the best way.  \ud83c\udde7\ud83c\udde7\ud83c\uddec\ud83c\udde7  \ud83d\udc69\ud83c\udffe\u200d\ud83d\udcbbDown Syndrome Parent\ud83d\udc96", "cluster": -1}, "1348921318142578688": {"username": "a6c05d7bd91246e", "bio": "He that spared not his own Son, but delivered him up for us all, how shall he not with him also freely give us all things?\r\nRomans 8:32", "cluster": -1}, "1348990228179144704": {"username": "heff_jan", "bio": "loves the Steelers ,the Ocean, traveling, strong men.", "cluster": -1}, "1349020601265115142": {"username": "ThatABoy10", "bio": "Making things right", "cluster": -1}, "1349033833136607234": {"username": "mellow6191", "bio": "Legalize Cannabis Again", "cluster": 84}, "1349039150650023937": {"username": "debibailey12", "bio": "", "cluster": 84}, "1349419903233576962": {"username": "CherylMckinle20", "bio": "Retired elementary teacher, mom, progressive activist, environmentalist, reader. Collects flamingos.", "cluster": 84}}